apache_ranger/__init__.py
apache_ranger/exceptions.py
apache_ranger/utils.py
apache_ranger/client/__init__.py
apache_ranger/client/ranger_client.py
apache_ranger/client/ranger_kms_client.py
apache_ranger/client/ranger_user_mgmt_client.py
apache_ranger/model/__init__.py
apache_ranger/model/grant_revoke_role_request.py
apache_ranger/model/ranger_base.py
apache_ranger/model/ranger_kms.py
apache_ranger/model/ranger_policy.py
apache_ranger/model/ranger_principal.py
apache_ranger/model/ranger_role.py
apache_ranger/model/ranger_security_zone.py
apache_ranger/model/ranger_service.py
apache_ranger/model/ranger_service_def.py
apache_ranger/model/ranger_service_resource.py
apache_ranger/model/ranger_service_tags.py
apache_ranger/model/ranger_tag.py
apache_ranger/model/ranger_tagdef.py
apache_ranger/model/ranger_user_mgmt.py
apache_ranger-0.0.12.dist-info/LICENSE
apache_ranger-0.0.12.dist-info/METADATA
apache_ranger-0.0.12.dist-info/WHEEL
apache_ranger-0.0.12.dist-info/top_level.txt
apache_ranger-0.0.12.dist-info/RECORD
