Metadata-Version: 2.1
Name: apache-ranger
Version: 0.0.12
Summary: Apache Ranger Python client
Home-page: https://github.com/apache/ranger/tree/master/intg/src/main/python
Author: Apache Ranger
Author-email: dev@ranger.apache.org
License: Apache LICENSE 2.0
Keywords: ranger client,apache ranger
Platform: UNKNOWN
Classifier: Programming Language :: Python :: 2.7
Classifier: License :: OSI Approved :: Apache Software License
Classifier: Operating System :: OS Independent
Requires-Python: >=2.7
License-File: LICENSE
Requires-Dist: requests (>=2.24)
Requires-Dist: strenum (>=0.4.15)
